edb_noumea/__init__.py
edb_noumea/details.py
edb_noumea/main.py
edb_noumea-0.3.5.dist-info/licenses/LICENSE
edb_noumea-0.3.5.dist-info/METADATA
edb_noumea-0.3.5.dist-info/WHEEL
edb_noumea-0.3.5.dist-info/top_level.txt
edb_noumea-0.3.5.dist-info/RECORD
