Metadata-Version: 2.4
Name: edb-noumea
Version: 0.3.5
Summary: Scraper pour la qualité des eaux de baignade à Nouméa.
Project-URL: Homepage, https://github.com/adriens/edb-noumea
Project-URL: Repository, https://github.com/adriens/edb-noumea
License-File: LICENSE
Requires-Dist: requests
Requires-Dist: beautifulsoup4
Requires-Dist: pandas
Requires-Dist: lxml
Requires-Dist: pdfplumber
Requires-Dist: matplotlib
Dynamic: license-file
